xls2xlsx/__init__.py
xls2xlsx/cli.py
xls2xlsx/htmlxls2xlsx.py
xls2xlsx/utils.py
xls2xlsx/xls2xlsx.py
xls2xlsx-0.2.0.dist-info/AUTHORS.rst
xls2xlsx-0.2.0.dist-info/LICENSE
xls2xlsx-0.2.0.dist-info/METADATA
xls2xlsx-0.2.0.dist-info/WHEEL
xls2xlsx-0.2.0.dist-info/entry_points.txt
xls2xlsx-0.2.0.dist-info/top_level.txt
xls2xlsx-0.2.0.dist-info/RECORD
