Metadata-Version: 2.1
Name: xls2xlsx
Version: 0.2.0
Summary: Convert xls file to xlsx
Home-page: https://github.com/snoopyjc/xls2xlsx
Author: Joe Cool
Author-email: snoopyjc@gmail.com
License: MIT license
Keywords: xls2xlsx
Classifier: Development Status :: 4 - Beta
Classifier: Intended Audience :: Developers
Classifier: License :: OSI Approved :: MIT License
Classifier: Natural Language :: English
Classifier: Programming Language :: Python :: 3
Classifier: Programming Language :: Python :: 3.7
Classifier: Programming Language :: Python :: 3.8
Classifier: Programming Language :: Python :: 3.9
Classifier: Programming Language :: Python :: 3.10
Requires-Python: >=3.7
License-File: LICENSE
License-File: AUTHORS.rst
